benchmarks/__init__.py
benchmarks/benchmark_all_examples.py
benchmarks/benchmark_utils.py
benchmarks/profile_all_examples.py
benchmarks/run_all_examples.py
env_data/__init__.py
env_data/railway/__init__.py
env_data/railway/basic_elements_test.pkl
env_data/railway/complex_scene.pkl
env_data/railway/complex_scene_2.pkl
env_data/railway/example_flatland_000.pkl
env_data/railway/example_flatland_001.pkl
env_data/railway/example_network_000.pkl
env_data/railway/example_network_001.pkl
env_data/railway/example_network_002.pkl
env_data/railway/example_network_003.pkl
env_data/tests/Level_distance_map_shortest_path.mpk
env_data/tests/Test_2_Level_0.pkl
env_data/tests/Test_9_Level_1.pkl
env_data/tests/__init__.py
env_data/tests/test1.npy
env_data/tests/test_001.pkl
env_data/tests/test_002.mpk
env_data/tests/test_env_loop.pkl
env_data/tests/service_test/metadata.csv
env_data/tests/service_test/Test_0/Level_0.pkl
env_data/tests/service_test/Test_0/Level_1.pkl
examples/__init__.py
examples/custom_observation_example_01_SimpleObs.py
examples/custom_observation_example_02_SingleAgentNavigationObs.py
examples/custom_observation_example_03_ObservePredictions.py
examples/custom_railmap_example.py
examples/flatland_3_0_example.py
examples/flatland_performance_profiling.py
examples/introduction_flatland_3.py
examples/training_example.py
flatland/__init__.py
flatland/cli.py
flatland/action_plan/__init__.py
flatland/action_plan/action_plan.py
flatland/action_plan/action_plan_player.py
flatland/core/__init__.py
flatland/core/env.py
flatland/core/env_observation_builder.py
flatland/core/env_prediction_builder.py
flatland/core/transition_map.py
flatland/core/transitions.py
flatland/core/grid/__init__.py
flatland/core/grid/grid4.py
flatland/core/grid/grid4_astar.py
flatland/core/grid/grid4_utils.py
flatland/core/grid/grid8.py
flatland/core/grid/grid_utils.py
flatland/core/grid/rail_env_grid.py
flatland/envs/__init__.py
flatland/envs/agent_chains.py
flatland/envs/agent_utils.py
flatland_rl_optimised_code-3.0.16.dist-info/AUTHORS.md
flatland_rl_optimised_code-3.0.16.dist-info/LICENSE
flatland_rl_optimised_code-3.0.16.dist-info/METADATA
flatland_rl_optimised_code-3.0.16.dist-info/WHEEL
flatland_rl_optimised_code-3.0.16.dist-info/entry_points.txt
flatland_rl_optimised_code-3.0.16.dist-info/top_level.txt
flatland_rl_optimised_code-3.0.16.dist-info/RECORD
