Metadata-Version: 2.1
Name: flatland-rl-optimised-code
Version: 3.0.16
Summary: Multi Agent Reinforcement Learning on Trains
Home-page: https://gitlab.aicrowd.com/flatland/flatland
Author: S.P. Mohanty
Author-email: mohanty@aicrowd.com
License: UNKNOWN
Keywords: flatland
Platform: UNKNOWN
Classifier: Development Status :: 4 - Beta
Classifier: Intended Audience :: Developers
Classifier: Natural Language :: English
Classifier: Programming Language :: Python :: 3.6
Classifier: Programming Language :: Python :: 3.7
License-File: LICENSE
License-File: AUTHORS.md
Requires-Dist: tox (>=3.5.2)
Requires-Dist: pytest (<5,>=3.8.2)
Requires-Dist: pytest-runner (>=4.2)
Requires-Dist: Click (>=7.0)
Requires-Dist: crowdai-api (>=0.1.21)
Requires-Dist: numpy (>=1.16.2)
Requires-Dist: recordtype (>=1.3)
Requires-Dist: matplotlib (>=3.0.2)
Requires-Dist: Pillow (>=5.4.1)
Requires-Dist: msgpack (<2.0.0,>=1.0.0)
Requires-Dist: msgpack-numpy (>=0.4.4.0)
Requires-Dist: svgutils (>=0.3.1)
Requires-Dist: pyarrow (>=0.13.0)
Requires-Dist: pandas (>=0.25.1)
Requires-Dist: importlib-metadata (>=0.17)
Requires-Dist: importlib-resources (<2,>=1.0.1)
Requires-Dist: six (>=1.12.0)
Requires-Dist: timeout-decorator (>=0.4.1)
Requires-Dist: attrs
Requires-Dist: gym (==0.14.0)
Requires-Dist: networkx
Requires-Dist: ipycanvas
Requires-Dist: graphviz
Requires-Dist: imageio
Requires-Dist: dataclasses
